matrixlib/__init__.py
matrixlib/builtins.py
matrixlib/meshes.py
matrixlib/py.typed
matrixlib/rule.py
matrixlib/typing.py
matrixlib-0.3.2.dist-info/LICENSE
matrixlib-0.3.2.dist-info/METADATA
matrixlib-0.3.2.dist-info/WHEEL
matrixlib-0.3.2.dist-info/top_level.txt
matrixlib-0.3.2.dist-info/RECORD
