Metadata-Version: 2.1
Name: matrixlib
Version: 0.3.2
Summary: General-purpose matrices for the layman
Author: Braedyn L
License: MIT License
Project-URL: Homepage, https://braedynl.github.io/matrixlib/
Project-URL: Documentation, https://braedynl.github.io/matrixlib/
Project-URL: Source, https://github.com/braedynl/matrixlib
Project-URL: Bug Tracker, https://github.com/braedynl/matrixlib/issues
Keywords: matrices,matrix,vectors,vector,vectorization,sequences
Classifier: Programming Language :: Python :: 3
Classifier: Programming Language :: Python :: 3.9
Classifier: Programming Language :: Python :: 3.10
Classifier: Programming Language :: Python :: 3.11
Classifier: License :: OSI Approved :: MIT License
Classifier: Operating System :: OS Independent
Classifier: Topic :: Software Development :: Libraries :: Python Modules
Requires-Python: >=3.9
License-File: LICENSE
Requires-Dist: typing-extensions (>=4.0.1)
